xy_web_settings/Mode.py
xy_web_settings/ModuleData.py
xy_web_settings/Settings.py
xy_web_settings/__init__.py
xy_web_settings/Section/Section.py
xy_web_settings/Section/__init__.py
xy_web_settings/Section/Admin/Admin.py
xy_web_settings/Section/Admin/__init__.py
xy_web_settings/Section/Backup/Backup.py
xy_web_settings/Section/Backup/__init__.py
xy_web_settings/Section/Database/Database.py
xy_web_settings/Section/Database/__init__.py
xy_web_settings/Section/Development/Development.py
xy_web_settings/Section/Development/__init__.py
xy_web_settings/Section/Log/Log.py
xy_web_settings/Section/Log/__init__.py
xy_web_settings/Section/Nginx/Nginx.py
xy_web_settings/Section/Nginx/__init__.py
xy_web_settings/Section/Resource/Resource.py
xy_web_settings/Section/Resource/__init__.py
xy_web_settings/Section/Server/Server.py
xy_web_settings/Section/Server/__init__.py
xy_web_settings/Section/Site/Site.py
xy_web_settings/Section/Site/__init__.py
xy_web_settings/Section/Source/Source.py
xy_web_settings/Section/Source/__init__.py
xy_web_settings/Section/Workspace/Workspace.py
xy_web_settings/Section/Workspace/__init__.py
xy_web_settings/data/template/config/full/settings_toml.template
xy_web_settings/data/template/config/simple/settings_toml.template
xy_web_settings-1.0.4.dist-info/LICENSE
xy_web_settings-1.0.4.dist-info/METADATA
xy_web_settings-1.0.4.dist-info/WHEEL
xy_web_settings-1.0.4.dist-info/top_level.txt
xy_web_settings-1.0.4.dist-info/RECORD
