Metadata-Version: 2.1
Name: xy_web_settings
Version: 1.0.4
Summary: xy-web-service服务设置模块
Author-email: 余洋 <yuyangit.0515@qq.com>
Classifier: Programming Language :: Python :: 3
Requires-Python: >=3.11.3
License-File: LICENSE
Requires-Dist: importlib-resources
Requires-Dist: xy-file
Requires-Dist: xy-configure
Requires-Dist: xy-settings
Requires-Dist: xy-work
